data_extractor/__init__.py
data_extractor/from_excel.py
data_extractor/from_gui.py
data_extractor/from_json_file.py
data_extractor/from_logging.py
data_extractor/opencv.py
data_extractor/test2.py
data_processing/__init__.py
data_processing/array.py
data_processing/image.py
data_processing/processing.py
data_processing/statistics.py
database/__init__.py
database/actions.py
database/function_usage.py
database/general_functionality.py
notion/__init__.py
notion/database.py
notion/page.py
tiger_brokers/__init__.py
tiger_brokers/configuration.py
tiger_brokers/option_api.py
tiger_brokers/stock_api.py
tiger_brokers/utilities.py
user_automation/__init__.py
user_automation/key_press.py
visualisation/__init__.py
visualisation/popup.py
visualisation/visualise.py
personal_custom_packages-0.1.dist-info/METADATA
personal_custom_packages-0.1.dist-info/WHEEL
personal_custom_packages-0.1.dist-info/top_level.txt
personal_custom_packages-0.1.dist-info/RECORD
