Metadata-Version: 2.1
Name: personal-custom-packages
Version: 0.1
Summary: A wrapper on existing modules and other operations I commonly use.
Home-page: https://github.com/yourusername/mypackage
Author: Marcus
Author-email: marcusongkiansiong@gmail.com
License: UNKNOWN
Platform: UNKNOWN
Classifier: Programming Language :: Python :: 3
Classifier: License :: OSI Approved :: MIT License
Classifier: Operating System :: OS Independent
Requires-Python: >=3.6
